lobi/__init__.py
lobi/bootstrap.py
lobi/cli.py
lobi/lobi.py
lobi/memory.py
lobi/tools.py
lobi_cli-0.3.0.dist-info/licenses/LICENSE
lobi_cli-0.3.0.dist-info/METADATA
lobi_cli-0.3.0.dist-info/WHEEL
lobi_cli-0.3.0.dist-info/entry_points.txt
lobi_cli-0.3.0.dist-info/top_level.txt
lobi_cli-0.3.0.dist-info/RECORD
