Metadata-Version: 2.4
Name: lobi-cli
Version: 0.3.0
Summary: Lobi: a terminal-based AI assistant with personality and tools
Home-page: https://github.com/ginkorea/lobi
Author: Josh Gompert
Classifier: Programming Language :: Python :: 3
Classifier: Environment :: Console
Classifier: License :: OSI Approved :: GNU General Public License v3 (GPLv3)
Classifier: Operating System :: OS Independent
Requires-Python: >=3.7
License-File: LICENSE
Requires-Dist: openai>=1.0.0
Requires-Dist: rich
Requires-Dist: python-dotenv
Requires-Dist: beautifulsoup4
Requires-Dist: requests
Requires-Dist: faiss-cpu
Requires-Dist: numpy
Dynamic: author
Dynamic: classifier
Dynamic: description
Dynamic: description-content-type
Dynamic: home-page
Dynamic: license-file
Dynamic: requires-dist
Dynamic: requires-python
Dynamic: summary
